{
"type": "FeatureCollection",
"name": "Layer #0",
"crs": { "type": "name", "properties": { "name": "urn:ogc:def:crs:OGC:1.3:CRS84" } },
"features": [
{ "type": "Feature", "properties": { "Name": "23279", "Description": "" }, "geometry": { "type": "Point", "coordinates": [ -77.412887, 37.58397, 0.0 ] } }
]
}
