{
"type": "FeatureCollection",
"name": "Layer #0",
"crs": { "type": "name", "properties": { "name": "urn:ogc:def:crs:OGC:1.3:CRS84" } },
"features": [
{ "type": "Feature", "properties": { "Name": "23441", "Description": "" }, "geometry": { "type": "Point", "coordinates": [ -75.702531, 37.711744, 0.0 ] } }
]
}
