{
"type": "FeatureCollection",
"name": "Layer #0",
"crs": { "type": "name", "properties": { "name": "urn:ogc:def:crs:OGC:1.3:CRS84" } },
"features": [
{ "type": "Feature", "properties": { "Name": "24043", "Description": "" }, "geometry": { "type": "Point", "coordinates": [ -79.933391, 37.277382, 0.0 ] } }
]
}
