{
"type": "FeatureCollection",
"name": "Layer #0",
"crs": { "type": "name", "properties": { "name": "urn:ogc:def:crs:OGC:1.3:CRS84" } },
"features": [
{ "type": "Feature", "properties": { "Name": "24505", "Description": "" }, "geometry": { "type": "Point", "coordinates": [ -79.14, 37.41, 0.0 ] } }
]
}
