{
"type": "FeatureCollection",
"name": "Layer #0",
"crs": { "type": "name", "properties": { "name": "urn:ogc:def:crs:OGC:1.3:CRS84" } },
"features": [
{ "type": "Feature", "properties": { "Name": "24535", "Description": "" }, "geometry": { "type": "Point", "coordinates": [ -78.919311, 36.611214, 0.0 ] } }
]
}
